unfurl.libs/libgcc_s-4e37474d.so.1
unfurl/reporting.py
unfurl/graphql.py
unfurl/projectpaths.py
unfurl/tosca_solver.abi3.so
unfurl/init.py
unfurl/configurator.py
unfurl/changelog-schema.json
unfurl/unfurl-schema.json
unfurl/manifest.py
unfurl/cloudmap.py
unfurl/to_json.py
unfurl/plan.py
unfurl/support.py
unfurl/solver.py
unfurl/packages.py
unfurl/util.py
unfurl/__init__.py
unfurl/yamlmanifest.py
unfurl/spec.py
unfurl/yamlloader.py
unfurl/runtime.py
unfurl/merge.py
unfurl/localenv.py
unfurl/repo.py
unfurl/__main__.py
unfurl/job.py
unfurl/testing.py
unfurl/result.py
unfurl/planrequests.py
unfurl/cloudmap-schema.json
unfurl/manifest-schema.json
unfurl/dsl.py
unfurl/logs.py
unfurl/eval.py
unfurl/venv.py
unfurl/py.typed
unfurl/lock.py
unfurl/skeletons/manifest.yaml.j2
unfurl/skeletons/secrets.yaml.j2
unfurl/skeletons/manifest-template.yaml.j2
unfurl/skeletons/local-unfurl-template.yaml.j2
unfurl/skeletons/service-template.yaml.j2
unfurl/skeletons/unfurl.local.yaml.j2
unfurl/skeletons/gitignore.j2
unfurl/skeletons/unfurl.yaml.j2
unfurl/skeletons/service_template.py.j2
unfurl/skeletons/gcp/unfurl.yaml.j2
unfurl/skeletons/home/manifest-template.yaml.j2
unfurl/skeletons/home/unfurl.yaml.j2
unfurl/skeletons/digitalocean/unfurl.yaml.j2
unfurl/skeletons/dashboard/manifest.yaml.j2
unfurl/skeletons/dashboard/unfurl.yaml.j2
unfurl/skeletons/aws/unfurl.yaml.j2
unfurl/skeletons/k8s/unfurl.yaml.j2
unfurl/skeletons/azure/unfurl.yaml.j2
unfurl/configurators/supervisor.py
unfurl/configurators/k8s.py
unfurl/configurators/helm-template.yaml
unfurl/configurators/supervisor-template.yaml
unfurl/configurators/ansible.py
unfurl/configurators/terraform.py
unfurl/configurators/shell.py
unfurl/configurators/__init__.py
unfurl/configurators/ansible.cfg
unfurl/configurators/kompose.py
unfurl/configurators/dns-template.yaml
unfurl/configurators/dns.py
unfurl/configurators/docker-template.yaml
unfurl/configurators/gcp.py
unfurl-1.2.0.dist-info/top_level.txt
unfurl-1.2.0.dist-info/RECORD
unfurl-1.2.0.dist-info/LICENSE
unfurl-1.2.0.dist-info/entry_points.txt
unfurl-1.2.0.dist-info/METADATA
unfurl-1.2.0.dist-info/WHEEL
unfurl-1.2.0.dist-info/pbr.json
