Metadata-Version: 2.1
Name: unfurl
Version: 1.2.0
Summary: Use Git to record and deploy changes to your DevOps infrastructure
Author-email: Adam Souzis <adam@onecommons.org>
Project-URL: Homepage, https://www.unfurl.cloud
Project-URL: Documentation, https://docs.unfurl.run
Project-URL: Repository, https://github.com/onecommons/unfurl
Project-URL: Changelog, https://github.com/onecommons/unfurl/blob/main/CHANGELOG.md
Classifier: Development Status :: 4 - Beta
Classifier: Environment :: Console
Classifier: Intended Audience :: Developers
Classifier: Operating System :: OS Independent
Classifier: License :: OSI Approved :: MIT License
Classifier: Programming Language :: Python :: 3
Classifier: Programming Language :: Python :: 3.8
Classifier: Programming Language :: Python :: 3.9
Classifier: Programming Language :: Python :: 3.10
Classifier: Programming Language :: Python :: 3.11
Classifier: Programming Language :: Python :: 3.12
Classifier: Programming Language :: Python :: 3.13
Requires-Python: >=3.8
License-File: LICENSE
Requires-Dist: pipenv==2024.0.0
Requires-Dist: click<8.1.4,>=8.0.1
Requires-Dist: jsonschema[format_nongpl]
Requires-Dist: ruamel.yaml==0.17.21
Requires-Dist: ansible-core<=2.15.9,>=2.11.12
Requires-Dist: rich==12.4.4
Requires-Dist: rich-click>=1.8.0
Requires-Dist: MarkupSafe<=2.1.1
Requires-Dist: jinja2==3.1.4
Requires-Dist: typing-extensions>=4.7
Requires-Dist: flask==2.3.3
Requires-Dist: flask-caching<=2.0.1
Requires-Dist: flask-cors==5.0.0
Requires-Dist: waitress
Requires-Dist: python-gitlab==3.13.0
Requires-Dist: tosca>=0.1.0
Requires-Dist: tenacity>=6.1.0
Requires-Dist: pbr==6.0.0
Requires-Dist: setuptools
Requires-Dist: cliff==3.10.1
Requires-Dist: PyYAML>=6.0
Requires-Dist: python-dateutil>=2.8
Requires-Dist: stevedore<=5.1.0,>=3.5.0
Requires-Dist: requests>=2.28
Requires-Dist: certifi
Requires-Dist: importlib-metadata<=4.12.0; python_version < "3.8"
Requires-Dist: GitPython==3.1.41; python_version >= "3.7"
Provides-Extra: full
Requires-Dist: docker[tls]; extra == "full"
Requires-Dist: requests<2.32.0; extra == "full"
Requires-Dist: kubernetes==24.2.0; extra == "full"
Requires-Dist: octodns==0.9.14; extra == "full"
Requires-Dist: boto3; extra == "full"
Requires-Dist: supervisor; extra == "full"
Requires-Dist: requests>=2.14.2; extra == "full"
Requires-Dist: google-cloud-compute==1.3.2; extra == "full"
Requires-Dist: google-cloud-dns==0.34.0; extra == "full"
Requires-Dist: google-auth; extra == "full"
Requires-Dist: gunicorn==22.0.0; extra == "full"
Requires-Dist: redis==4.4.4; extra == "full"
Provides-Extra: server
Requires-Dist: gunicorn==22.0.0; extra == "server"
Requires-Dist: redis==4.4.4; extra == "server"
